imqfody/__init__.py
imqfody/imqfody.py
imqfody-0.1.3.dist-info/LICENSE
imqfody-0.1.3.dist-info/WHEEL
imqfody-0.1.3.dist-info/METADATA
imqfody-0.1.3.dist-info/RECORD
